setup.py
sebastian/__init__.py
sebastian.egg-info/PKG-INFO
sebastian.egg-info/SOURCES.txt
sebastian.egg-info/dependency_links.txt
sebastian.egg-info/top_level.txt
sebastian/core/__init__.py
sebastian/core/elements.py
sebastian/core/notes.py
sebastian/core/transforms.py
sebastian/lilypond/__init__.py
sebastian/lilypond/interp.py
sebastian/midi/__init__.py
sebastian/midi/midi.py
sebastian/midi/player.py
sebastian/midi/write_midi.py