Metadata-Version: 1.0
Name: sebastian
Version: 0.0.3
Summary: symbolic music analysis and composition library in Python
Home-page: http://github.com/jtauber/sebastian
Author: James Tauber
Author-email: jtauber@jtauber.com
License: MIT
Platform: UNKNOWN
